nicegui_tic_tac_toe/__init__.py
nicegui_tic_tac_toe/py.typed
nicegui_tic_tac_toe/tic_tac_toe.py
nicegui_tic_tac_toe-0.1.6.dist-info/METADATA
nicegui_tic_tac_toe-0.1.6.dist-info/WHEEL
nicegui_tic_tac_toe-0.1.6.dist-info/entry_points.txt
nicegui_tic_tac_toe-0.1.6.dist-info/licenses/LICENSE
nicegui_tic_tac_toe-0.1.6.dist-info/RECORD
