Metadata-Version: 2.4
Name: nicegui-tic_tac_toe
Version: 0.1.6
Summary: TicTacToe on NiceGUI
Project-URL: homepage, https://github.com/SaitoTsutomu/nicegui-tic_tac_toe
Author-email: Saito Tsutomu <tsutomu7@hotmail.co.jp>
License-File: LICENSE
Classifier: Development Status :: 1 - Planning
Classifier: License :: OSI Approved :: Apache Software License
Classifier: Programming Language :: Python
Classifier: Topic :: Scientific/Engineering
Classifier: Topic :: Software Development
Requires-Python: >=3.12
Requires-Dist: fire>=0.7.0
Requires-Dist: nicegui>=2.11.1
